molbox/__init__.py
molbox/box.py
molbox/lammps_data.py
molbox/molbox.py
molbox/rdkit_3d_ops.py
molbox-0.1.4.dist-info/LICENSE
molbox-0.1.4.dist-info/METADATA
molbox-0.1.4.dist-info/WHEEL
molbox-0.1.4.dist-info/RECORD
