Metadata-Version: 2.1
Name: molbox
Version: 0.1.4
Summary: Create simulation boxes for LAMMPS.
Author: Niklas Kappel
Author-email: niklas.kappel@kit.edu
Requires-Python: >=3.9,<4.0
Classifier: Programming Language :: Python :: 3
Classifier: Programming Language :: Python :: 3.9
Classifier: Programming Language :: Python :: 3.10
Classifier: Programming Language :: Python :: 3.11
Classifier: Programming Language :: Python :: 3.12
Requires-Dist: openbabel-wheel (>=3.1.1.19,<4.0.0.0)
Requires-Dist: rdkit (>=2023.9.5,<2024.0.0)
Requires-Dist: scipy (>=1.13.0,<2.0.0)
Project-URL: repository, https://github.com/NiklasKappel/molbox
